MANIFEST.in
setup.py
clue/__init__.py
clue/completion.py
clue/feature.py
clue/hooks.py
clue/output.py
clue.egg-info/PKG-INFO
clue.egg-info/SOURCES.txt
clue.egg-info/dependency_links.txt
clue.egg-info/entry_points.txt
clue.egg-info/not-zip-safe
clue.egg-info/requires.txt
clue.egg-info/top_level.txt
clue/blueprint/clash.yaml
clue/blueprint/cloudify-dev/blueprint.yaml
clue/blueprint/cloudify-dev/operations/__init__.py
clue/blueprint/cloudify-dev/operations/common.py
clue/blueprint/cloudify-dev/operations/git.py
clue/blueprint/cloudify-dev/operations/idea.py
clue/blueprint/cloudify-dev/operations/operations.py
clue/blueprint/cloudify-dev/operations/pip.py
clue/blueprint/cloudify-dev/operations/virtualenv.sh
clue/blueprint/cloudify-dev/resources/commit-msg
clue/blueprint/cloudify-dev/resources/git-branch-state.sh
clue/blueprint/cloudify-dev/resources/git-retag-cloudify
clue/blueprint/cloudify-dev/resources/postactivate
clue/blueprint/cloudify-dev/resources/idea/misc.xml
clue/blueprint/cloudify-dev/resources/idea/module.xml
clue/blueprint/cloudify-dev/resources/idea/modules.xml
clue/blueprint/cloudify-dev/resources/idea/vcs.xml