Metadata-Version: 1.0
Name: clue
Version: 0.40
Summary: Cloudify development environment CLI
Home-page: UNKNOWN
Author: GigaSpaces
Author-email: cosmo-admin@gigaspaces.com
License: Apache License, Version 2.0
Platform: UNKNOWN
